kbg/__init__.py
kbg-0.0.5.dist-info/LICENSE
kbg-0.0.5.dist-info/METADATA
kbg-0.0.5.dist-info/WHEEL
kbg-0.0.5.dist-info/top_level.txt
kbg-0.0.5.dist-info/RECORD
