Metadata-Version: 2.1
Name: kbg
Version: 0.0.5
Summary: Python wrapper for the Kelbongoo website
Home-page: https://github.com/bfontaine/pykbg
Author: Baptiste Fontaine
Author-email: b@ptistefontaine.fr
License: MIT License
Platform: UNKNOWN
Classifier: Environment :: Console
Classifier: License :: OSI Approved :: MIT License
Classifier: Programming Language :: Python :: 3
Classifier: Programming Language :: Python :: 3.6
Classifier: Programming Language :: Python :: 3.7
Requires-Python: >=3.5
Requires-Dist: requests
